ortpy/LICENSE
ortpy/__init__.py
ortpy/__init__.pyi
ortpy/_ortpy.cp313-win_amd64.pyd
ortpy/_ortpy.pyi
ortpy/py.typed
ortpy-1.23b0.dist-info/METADATA
ortpy-1.23b0.dist-info/WHEEL
ortpy-1.23b0.dist-info/RECORD
