Metadata-Version: 2.2
Name: ortpy
Version: 1.23b0
Summary: ONNX runtime python binding
Author: Feng Wang
Classifier: Programming Language :: Python
Classifier: Programming Language :: Python :: 3
Classifier: Programming Language :: Python :: Implementation :: CPython
Classifier: Programming Language :: C++
Classifier: License :: OSI Approved :: MIT License
Classifier: Operating System :: Microsoft :: Windows
Project-URL: Homepage, https://github.com/chemwolf6922/onnxruntime.py
Requires-Python: >=3.10
Requires-Dist: numpy
Provides-Extra: with-lib
Requires-Dist: ortpy_lib~=1.23.0; extra == "with-lib"
